Workbook

Sheet Tabela
A1: Cód. | B1: Município | C1: 2002 | D1: 2003 | E1: 2004 | F1: 2005 | G1: 2006 | H1: 2007 | I1: 2008 | J1: 2009 | K1: 2010 | L1: 2011 | M1: 2012 | N1: 2013 | O1: 2014 | P1: 2015 | Q1: 2016 | R1: 2017 | S1: 2018 | T1: 2019 | U1: 2020 | V1: 2021
A2: 1100015 | B2: Alta Floresta D'Oeste (RO) | C2: 27237 | D2: 27563 | E2: 29001 | F2: 28629 | G2: 29005 | H2: =(I2+G2)/2 -> 26791 | I2: 24577 | J2: 24354 | K2: =(L2+J2)/2 -> 24291 | L2: 24228 | M2: 24069 | N2: 25728 | O2: 25652 | P2: 25578 | Q2: 25506 | R2: 25437 | S2: 23167 | T2: 22945 | U2: 22728 | V2: 22516
A3: 1100023 | B3: Ariquemes (RO) | C3: 78039 | D3: 79680 | E3: 86901 | F3: 85031 | G3: 86924 | H3: =(I3+G3)/2 -> 85752.5 | I3: 84581 | J3: 85541 | K3: =(L3+J3)/2 -> 88555.5 | L3: 91570 | M3: 92747 | N3: 101269 | O3: 102860 | P3: 104401 | Q3: 105896 | R3: 107345 | S3: 106168 | T3: 107863 | U3: 109523 | V3: 111148
A4: 1100031 | B4: Cabixi (RO) | C4: 7490 | D4: 7478 | E4: 7421 | F4: 7436 | G4: 7421 | H4: =(I4+G4)/2 -> 7099 | I4: 6777 | J4: 6695 | K4: =(L4+J4)/2 -> 6458 | L4: 6221 | M4: 6132 | N4: 6495 | O4: 6424 | P4: 6355 | Q4: 6289 | R4: 6224 | S4: 5438 | T4: 5312 | U4: 5188 | V4: 5067
A5: 1100049 | B5: Cacoal (RO) | C5: 74381 | D5: 74758 | E5: 76417 | F5: 75988 | G5: 76422 | H5: =(I5+G5)/2 -> 77342.5 | I5: 78263 | J5: 78675 | K5: =(L5+J5)/2 -> 78817 | L5: 78959 | M5: 79330 | N5: 85863 | O5: 86556 | P5: 87226 | Q5: 87877 | R5: 88507 | S5: 84813 | T5: 85359 | U5: 85893 | V5: 86416
A6: 1100056 | B6: Cerejeiras (RO) | C6: 17925 | D6: 17794 | E6: 17217 | F6: 17366 | G6: 17215 | H6: =(I6+G6)/2 -> 16999.5 | I6: 16784 | J6: 16622 | K6: =(L6+J6)/2 -> 16780.5 | L6: 16939 | M6: 16852 | N6: 18041 | O6: 18013 | P6: 17986 | Q6: 17959 | R6: 17934 | S6: 16444 | T6: 16323 | U6: 16204 | V6: 16088
A7: 1100064 | B7: Colorado do Oeste (RO) | C7: 20881 | D7: 20412 | E7: 18349 | F7: 18883 | G7: 18342 | H7: =(I7+G7)/2 -> 18279 | I7: 18216 | J7: 17822 | K7: =(L7+J7)/2 -> 18080 | L7: 18338 | M7: 18093 | N7: 19190 | O7: 19001 | P7: 18817 | Q7: 18639 | R7: 18467 | S7: 16227 | T7: 15882 | U7: 15544 | V7: 15213
A8: 1100072 | B8: Corumbiara (RO) | C8: 10160 | D8: 10022 | E8: 9411 | F8: 9569 | G8: 9409 | H8: =(I8+G8)/2 -> 9585 | I8: 9761 | J8: 9680 | K8: =(L8+J8)/2 -> 9167.5 | L8: 8655 | M8: 8530 | N8: 9036 | O8: 8938 | P8: 8842 | Q8: 8749 | R8: 8659 | S8: 7567 | T8: 7391 | U8: 7220 | V8: 7052
A9: 1100080 | B9: Costa Marques (RO) | C9: 9919 | D9: 10255 | E9: 11731 | F9: 11349 | G9: 11735 | H9: =(I9+G9)/2 -> 12854 | I9: 13973 | J9: 14452 | K9: =(L9+J9)/2 -> 14237.5 | L9: 14023 | M9: 14355 | N9: 15853 | O9: 16258 | P9: 16651 | Q9: 17031 | R9: 17400 | S9: 17855 | T9: 18331 | U9: 18798 | V9: 19255
A10: 1100098 | B10: Espigão D'Oeste (RO) | C10: 26221 | D10: 26468 | E10: 27556 | F10: 27274 | G10: 27559 | H10: =(I10+G10)/2 -> 28088 | I10: 28617 | J10: 28892 | K10: =(L10+J10)/2 -> 28927.5 | L10: 28963 | M10: 29189 | N10: 31699 | O10: 32047 | P10: 32385 | Q10: 32712 | R10: 33030 | S10: 32047 | T10: 32374 | U10: 32695 | V10: 33009
A11: 1100106 | B11: Guajará-Mirim (RO) | C11: 39194 | D11: 39728 | E11: 42075 | F11: 41467 | G11: 42082 | H11: =(I11+G11)/2 -> 41311.5 | I11: 40541 | J11: 40762 | K11: =(L11+J11)/2 -> 41348 | L11: 41934 | M11: 42202 | N11: 45761 | O11: 46203 | P11: 46632 | Q11: 47048 | R11: 47451 | S11: 45783 | T11: 46174 | U11: 46556 | V11: 46930
A12: 1100114 | B12: Jaru (RO) | C12: 54352 | D12: 54701 | E12: 56238 | F12: 55840 | G12: 56242 | H12: =(I12+G12)/2 -> 55098.5 | I12: 53955 | J12: 53943 | K12: =(L12+J12)/2 -> 52913 | L12: 51883 | M12: 51765 | N12: 55597 | O12: 55669 | P12: 55738 | Q12: 55806 | R12: 55871 | S12: 51933 | T12: 51775 | U12: 51620 | V12: 51469
A13: 1100122 | B13: Ji-Paraná (RO) | C13: 108694 | D13: 109573 | E13: 113441 | F13: 112439 | G13: 113453 | H13: =(I13+G13)/2 -> 112080 | I13: 110707 | J13: 111010 | K13: =(L13+J13)/2 -> 114186.5 | L13: 117363 | M13: 118092 | N13: 128026 | O13: 129242 | P13: 130419 | Q13: 131560 | R13: 132667 | S13: 127907 | T13: 128969 | U13: 130009 | V13: 131026
... A225: 1504703 | B225: Moju (PA) | C225: 55583 | D225: 56810 | E225: 59592 | F225: 60809 | G225: 62223 | H225: =(I225+G225)/2 -> 64709 | I225: 67195 | J225: 68600 | K225: =(L225+J225)/2 -> 69964.5 | L225: 71329 | M225: 72597 | N225: 74768 | O225: 76096 | P225: 77385 | Q225: 78629 | R225: 79825 | S225: 80988 | T225: 82094 | U225: 83182 | V225: 84251
A226: 1504752 | B226: Mojuí dos Campos (PA) | C226: ... | D226: ... | E226: ... | F226: ... | G226: ... | H226: =(I226+G226)/2 -> #VALUE! | I226: ... | J226: ... | K226: =(L226+J226)/2 -> #VALUE! | L226: ... | M226: 15018 | N226: 15232 | O226: 15341 | P226: 15446 | Q226: 15548 | R226: 15646 | S226: 15982 | T226: 16084 | U226: 16184 | V226: 16282
A227: 1504802 | B227: Monte Alegre (PA) | C227: 62041 | D227: 63396 | E227: 66467 | F227: 67811 | G227: 69372 | H227: =(I227+G227)/2 -> 66457.5 | I227: 63543 | J227: 63941 | K227: =(L227+J227)/2 -> 59788.5 | L227: 55636 | M227: 55804 | N227: 56147 | O227: 56231 | P227: 56312 | Q227: 56391 | R227: 56466 | S227: 57900 | T227: 58032 | U227: 58162 | V227: 58289
A228: 1504901 | B228: Muaná (PA) | C228: 26119 | D228: 26422 | E228: 27109 | F228: 27409 | G228: 27758 | H228: =(I228+G228)/2 -> 28937.5 | I228: 30117 | J228: 30568 | K228: =(L228+J228)/2 -> 32721.5 | L228: 34875 | M228: 35524 | N228: 36632 | O228: 37314 | P228: 37977 | Q228: 38616 | R228: 39231 | S228: 39783 | T228: 40349 | U228: 40906 | V228: 41454
A229: 1504950 | B229: Nova Esperança do Piriá (PA) | C229: 21469 | D229: 22665 | E229: 25377 | F229: 26564 | G229: 27943 | H229: =(I229+G229)/2 -> 25771 | I229: 23599 | J229: 24062 | K229: =(L229+J229)/2 -> 22159 | L229: 20256 | M229: 20350 | N229: 20528 | O229: 20596 | P229: 20663 | Q229: 20727 | R229: 20789 | S229: 21291 | T229: 21368 | U229: 21444 | V229: 21519
A230: 1504976 | B230: Nova Ipixuna (PA) | C230: 12573 | D230: 12900 | E230: 13644 | F230: 13970 | G230: 14348 | H230: =(I230+G230)/2 -> 14578 | I230: 14808 | J230: 15097 | K230: =(L230+J230)/2 -> 14978 | L230: 14859 | M230: 15065 | N230: 15422 | O230: 15632 | P230: 15836 | Q230: 16032 | R230: 16221 | S230: 16499 | T230: 16678 | U230: 16854 | V230: 17027
A231: 1505007 | B231: Nova Timboteua (PA) | C231: 11822 | D231: 12016 | E231: 12454 | F231: 12646 | G231: 12869 | H231: =(I231+G231)/2 -> 12718.5 | I231: 12568 | J231: 12677 | K231: =(L231+J231)/2 -> 13260.5 | L231: 13844 | M231: 14012 | N231: 14305 | O231: 14472 | P231: 14635 | Q231: 14791 | R231: 14942 | S231: 15218 | T231: 15363 | U231: 15506 | V231: 15646
A232: 1505031 | B232: Novo Progresso (PA) | C232: 29018 | D232: 30907 | E232: 35192 | F232: 37067 | G232: 39245 | H232: =(I232+G232)/2 -> 30544 | I232: 21843 | J232: 21504 | K232: =(L232+J232)/2 -> 23321 | L232: 25138 | M232: 25151 | N232: 25203 | O232: 25169 | P232: 25135 | Q232: 25102 | R232: 25071 | S232: 25758 | T232: 25762 | U232: 25766 | V232: 25769
A233: 1505064 | B233: Novo Repartimento (PA) | C233: 44610 | D233: 45906 | E233: 48846 | F233: 50133 | G233: 51627 | H233: =(I233+G233)/2 -> 53066.5 | I233: 54506 | J233: 55762 | K233: =(L233+J233)/2 -> 59683 | L233: 63604 | M233: 65106 | N233: 67652 | O233: 69267 | P233: 70835 | Q233: 72347 | R233: 73802 | S233: 74602 | T233: 75919 | U233: 77214 | V233: 78488
A234: 1505106 | B234: Óbidos (PA) | C234: 47370 | D234: 47779 | E234: 48705 | F234: 49111 | G234: 49582 | H234: =(I234+G234)/2 -> 48934.5 | I234: 48287 | J234: 48429 | K234: =(L234+J234)/2 -> 48990.5 | L234: 49552 | M234: 49763 | N234: 50171 | O234: 50317 | P234: 50459 | Q234: 50596 | R234: 50727 | S234: 51964 | T234: 52137 | U234: 52306 | V234: 52473
A235: 1505205 | B235: Oeiras do Pará (PA) | C235: 24194 | D235: 24630 | E235: 25619 | F235: 26051 | G235: 26554 | H235: =(I235+G235)/2 -> 26520.5 | I235: 26487 | J235: 26796 | K235: =(L235+J235)/2 -> 27900.5 | L235: 29005 | M235: 29402 | N235: 30088 | O235: 30490 | P235: 30880 | Q235: 31257 | R235: 31619 | S235: 32168 | T235: 32512 | U235: 32850 | V235: 33182
A236: 1505304 | B236: Oriximiná (PA) | C236: 49945 | D236: 50694 | E236: 52392 | F236: 53135 | G236: 53999 | H236: =(I236+G236)/2 -> 55882 | I236: 57765 | J236: 58683 | K236: =(L236+J236)/2 -> 61294 | L236: 63905 | M236: 64978 | N236: 66821 | O236: 67939 | P236: 69024 | Q236: 70071 | R236: 71078 | S236: 72160 | T236: 73096 | U236: 74016 | V236: 74921
A237: 1505403 | B237: Ourém (PA) | C237: 14741 | D237: 14900 | E237: 15262 | F237: 15421 | G237: 15605 | H237: =(I237+G237)/2 -> 15662 | I237: 15719 | J237: 15841 | K237: =(L237+J237)/2 -> 16149.5 | L237: 16458 | M237: 16601 | N237: 16854 | O237: 16986 | P237: 17114 | Q237: 17237 | R237: 17356 | S237: 17721 | T237: 17842 | U237: 17961 | V237: 18079
A238: 1505437 | B238: Ourilândia do Norte (PA) | C238: 19637 | D238: 19714 | E238: 19889 | F238: 19965 | G238: 20054 | H238: =(I238+G238)/2 -> 20612.5 | I238: 21171 | J238: 21327 | K238: =(L238+J238)/2 -> 24646 | L238: 27965 | M238: 28551 | N238: 29547 | O238: 30171 | P238: 30776 | Q238: 31359 | R238: 31921 | S238: 32319 | T238: 32832 | U238: 33335 | V238: 33831
... A681: 2200905 | B681: Aroazes (PI) | C681: 6065 | D681: 6083 | E681: 6122 | F681: 6143 | G681: 6165 | H681: =(I681+G681)/2 -> 6095 | I681: 6025 | J681: 6019 | K681: =(L681+J681)/2 -> 5890 | L681: 5761 | M681: 5742 | N681: 5784 | O681: 5773 | P681: 5763 | Q681: 5755 | R681: 5748 | S681: 5844 | T681: 5835 | U681: 5827 | V681: 5819
A682: 2200954 | B682: Aroeiras do Itaim (PI) | C682: ... | D682: ... | E682: 2561 | F682: 2591 | G682: 2620 | H682: =(I682+G682)/2 -> 2675.5 | I682: 2731 | J682: 2759 | K682: =(L682+J682)/2 -> 2600 | L682: 2441 | M682: 2442 | N682: 2459 | O682: 2460 | P682: 2460 | Q682: 2460 | R682: 2511 | S682: 2551 | T682: 2551 | U682: 2551 | V682: 2551
A683: 2201002 | B683: Arraial (PI) | C683: 4848 | D683: 4820 | E683: 4760 | F683: 4727 | G683: 4695 | H683: =(I683+G683)/2 -> 4920 | I683: 5145 | J683: 5165 | K683: =(L683+J683)/2 -> 4918.5 | L683: 4672 | M683: 4655 | N683: 4688 | O683: 4678 | P683: 4670 | Q683: 4662 | R683: 4656 | S683: 4735 | T683: 4727 | U683: 4720 | V683: 4713
A684: 2201051 | B684: Assunção do Piauí (PI) | C684: 7085 | D684: 7155 | E684: 7303 | F684: 7385 | G684: 7467 | H684: =(I684+G684)/2 -> 7855 | I684: 8243 | J684: 8370 | K684: =(L684+J684)/2 -> 7958.5 | L684: 7547 | M684: 7590 | N684: 7645 | O684: 7667 | P684: 7686 | Q684: 7703 | R684: 7717 | S684: 7828 | T684: 7846 | U684: 7863 | V684: 7879
A685: 2201101 | B685: Avelino Lopes (PI) | C685: 9853 | D685: 9959 | E685: 10373 | F685: 10497 | G685: 10620 | H685: =(I685+G685)/2 -> 11230 | I685: 11840 | J685: 12039 | K685: =(L685+J685)/2 -> 11601.5 | L685: 11164 | M685: 11258 | N685: 11341 | O685: 11390 | P685: 11433 | Q685: 11471 | R685: 11503 | S685: 11252 | T685: 11289 | U685: 11326 | V685: 11361
A686: 2201150 | B686: Baixa Grande do Ribeiro (PI) | C686: 8118 | D686: 8275 | E686: 8605 | F686: 8787 | G686: 8968 | H686: =(I686+G686)/2 -> 9749.5 | I686: 10531 | J686: 10804 | K686: =(L686+J686)/2 -> 10765.5 | L686: 10727 | M686: 10930 | N686: 11014 | O686: 11123 | P686: 11218 | Q686: 11302 | R686: 11375 | S686: 11497 | T686: 11586 | U686: 11671 | V686: 11751
A687: 2201176 | B687: Barra D'Alcântara (PI) | C687: 4048 | D687: 4021 | E687: 3679 | F687: 3650 | G687: 3621 | H687: =(I687+G687)/2 -> 3751.5 | I687: 3882 | J687: 3886 | K687: =(L687+J687)/2 -> 3870.5 | L687: 3855 | M687: 3858 | N687: 3886 | O687: 3886 | P687: 3887 | Q687: 3888 | R687: 3889 | S687: 3950 | T687: 3951 | U687: 3952 | V687: 3953
A688: 2201200 | B688: Barras (PI) | C688: 41464 | D688: 41730 | E688: 42288 | F688: 42596 | G688: 42903 | H688: =(I688+G688)/2 -> 43738.5 | I688: 44574 | J688: 44913 | K688: =(L688+J688)/2 -> 45033.5 | L688: 45154 | M688: 45448 | N688: 45786 | O688: 45938 | P688: 46072 | Q688: 46189 | R688: 46291 | S688: 46941 | T688: 47066 | U688: 47185 | V688: 47298
A689: 2201309 | B689: Barreiras do Piauí (PI) | C689: 3144 | D689: 3165 | E689: 3210 | F689: 3235 | G689: 3259 | H689: =(I689+G689)/2 -> 3355.5 | I689: 3452 | J689: 3485 | K689: =(L689+J689)/2 -> 3365 | L689: 3245 | M689: 3255 | N689: 3278 | O689: 3283 | P689: 3287 | Q689: 3291 | R689: 3294 | S689: 3344 | T689: 3348 | U689: 3352 | V689: 3356
A690: 2201408 | B690: Barro Duro (PI) | C690: 6941 | D690: 7012 | E690: 7162 | F690: 7244 | G690: 7327 | H690: =(I690+G690)/2 -> 7089.5 | I690: 6852 | J690: 6853 | K690: =(L690+J690)/2 -> 6723.5 | L690: 6594 | M690: 6580 | N690: 6627 | O690: 6941 | P690: 6935 | Q690: 6930 | R690: 6925 | S690: 7038 | T690: 7032 | U690: 7027 | V690: 7022
A691: 2201507 | B691: Batalha (PI) | C691: 24813 | D691: 25131 | E691: 25800 | F691: 26169 | G691: 26536 | H691: =(I691+G691)/2 -> 26500.5 | I691: 26465 | J691: 26681 | K691: =(L691+J691)/2 -> 26291 | L691: 25901 | M691: 26023 | N691: 26215 | O691: 26277 | P691: 26331 | Q691: 26379 | R691: 26421 | S691: 26806 | T691: 26857 | U691: 26905 | V691: 26951
A692: 2201556 | B692: Bela Vista do Piauí (PI) | C692: 2935 | D692: 2923 | E692: 2896 | F692: 2881 | G692: 2866 | H692: =(I692+G692)/2 -> 3295.5 | I692: 3725 | J692: 3762 | K692: =(L692+J692)/2 -> 3789.5 | L692: 3817 | M692: 3854 | N692: 3882 | O692: 3902 | P692: 3919 | Q692: 3934 | R692: 3947 | S692: 3999 | T692: 4015 | U692: 4030 | V692: 4044
A693: 2201572 | B693: Belém do Piauí (PI) | C693: 2447 | D693: 2455 | E693: 2473 | F693: 2482 | G693: 2492 | H693: =(I693+G693)/2 -> 2680.5 | I693: 2869 | J693: 2912 | K693: =(L693+J693)/2 -> 3124.5 | L693: 3337 | M693: 3388 | N693: 3413 | O693: 3440 | P693: 3464 | Q693: 3485 | R693: 3503 | S693: 3544 | T693: 3566 | U693: 3587 | V693: 3607
A694: 2201606 | B694: Beneditinos (PI) | C694: 9643 | D694: 9611 | E694: 9544 | F694: 9500 | G694: 9463 | H694: =(I694+G694)/2 -> 9648 | I694: 9833 | J694: 9837 | K694: =(L694+J694)/2 -> 9882 | L694: 9927 | M694: 9943 | N694: 10014 | O694: 10021 | P694: 10027 | Q694: 10032 | R694: 10037 | S694: 10462 | T694: 10467 | U694: 10473 | V694: 10479
... A804: 2206704 | B804: Nazaré do Piauí (PI) | C804: 7800 | D804: 7797 | E804: 7792 | F804: 7789 | G804: 7786 | H804: =(I804+G804)/2 -> 7465 | I804: 7144 | J804: 7070 | K804: =(L804+J804)/2 -> 7177 | L804: 7284 | M804: 7248 | N804: 7300 | O804: 7279 | P804: 7261 | Q804: 7245 | R804: 7231 | S804: 7356 | T804: 7339 | U804: 7322 | V804: 7307
A805: 2206720 | B805: Nazária (PI) | C805: ... | D805: ... | E805: ... | F805: ... | G805: ... | H805: =(I805+G805)/2 -> #VALUE! | I805: 7817 | J805: 7895 | K805: =(L805+J805)/2 -> 8022 | L805: 8149 | M805: 8227 | N805: 8289 | O805: 8330 | P805: 8366 | Q805: 8398 | R805: 8425 | S805: 8536 | T805: 8570 | U805: 8602 | V805: 8632
A806: 2206753 | B806: Nossa Senhora de Nazaré (PI) | C806: 3904 | D806: 3922 | E806: 3960 | F806: 3982 | G806: 4002 | H806: =(I806+G806)/2 -> 4083.5 | I806: 4165 | J806: 4192 | K806: =(L806+J806)/2 -> 4401 | L806: 4610 | M806: 4661 | N806: 4696 | O806: 4723 | P806: 4747 | Q806: 4768 | R806: 4786 | S806: 4847 | T806: 4870 | U806: 4891 | V806: 4911
A807: 2206803 | B807: Nossa Senhora dos Remédios (PI) | C807: 7453 | D807: 7564 | E807: 7797 | F807: 7926 | G807: 8054 | H807: =(I807+G807)/2 -> 8165 | I807: 8276 | J807: 8378 | K807: =(L807+J807)/2 -> 8330.5 | L807: 8283 | M807: 8356 | N807: 8419 | O807: 8457 | P807: 8491 | Q807: 8521 | R807: 8547 | S807: 8661 | T807: 8692 | U807: 8723 | V807: 8751
A808: 2206902 | B808: Novo Oriente do Piauí (PI) | C808: 6769 | D808: 6773 | E808: 6782 | F808: 6787 | G808: 6792 | H808: =(I808+G808)/2 -> 6579.5 | I808: 6367 | J808: 6321 | K808: =(L808+J808)/2 -> 6399.5 | L808: 6478 | M808: 6459 | N808: 6505 | O808: 6493 | P808: 6483 | Q808: 6474 | R808: 6466 | S808: 6575 | T808: 6565 | U808: 6556 | V808: 6548
A809: 2206951 | B809: Novo Santo Antônio (PI) | C809: 3144 | D809: 3139 | E809: 3129 | F809: 2779 | G809: 2774 | H809: =(I809+G809)/2 -> 3127.5 | I809: 3481 | J809: 3547 | K809: =(L809+J809)/2 -> 3421 | L809: 3295 | M809: 3329 | N809: 3354 | O809: 3371 | P809: 3387 | Q809: 2930 | R809: 2940 | S809: 2979 | T809: 2991 | U809: 3003 | V809: 3014
A810: 2207009 | B810: Oeiras (PI) | C810: 34339 | D810: 34538 | E810: 34760 | F810: 34989 | G810: 35218 | H810: =(I810+G810)/2 -> 35650 | I810: 36082 | J810: 36293 | K810: =(L810+J810)/2 -> 36040.5 | L810: 35788 | M810: 35931 | N810: 36195 | O810: 36266 | P810: 36329 | Q810: 36385 | R810: 36432 | S810: 36971 | T810: 37029 | U810: 37085 | V810: 37138
A811: 2207108 | B811: Olho D'Água do Piauí (PI) | C811: 2213 | D811: 2181 | E811: 2113 | F811: 2076 | G811: 2038 | H811: =(I811+G811)/2 -> 2375.5 | I811: 2713 | J811: 2755 | K811: =(L811+J811)/2 -> 2704 | L811: 2653 | M811: 2678 | N811: 2698 | O811: 2390 | P811: 2400 | Q811: 2409 | R811: 2417 | S811: 2449 | T811: 2459 | U811: 2468 | V811: 2477
A812: 2207207 | B812: Padre Marcos (PI) | C812: 7291 | D812: 7343 | E812: 7453 | F812: 7514 | G812: 7574 | H812: =(I812+G812)/2 -> 7562.5 | I812: 7551 | J812: 7582 | K812: =(L812+J812)/2 -> 7127.5 | L812: 6673 | M812: 6687 | N812: 6735 | O812: 6742 | P812: 6748 | Q812: 6753 | R812: 6758 | S812: 6862 | T812: 6868 | U812: 6873 | V812: 6879
A813: 2207306 | B813: Paes Landim (PI) | C813: 4157 | D813: 4144 | E813: 4117 | F813: 4103 | G813: 4088 | H813: =(I813+G813)/2 -> 4302.5 | I813: 4517 | J813: 4562 | K813: =(L813+J813)/2 -> 4308 | L813: 4054 | M813: 4049 | N813: 4077 | O813: 4074 | P813: 4071 | Q813: 4068 | R813: 4065 | S813: 4132 | T813: 4129 | U813: 4126 | V813: 4124
A814: 2207355 | B814: Pajeú do Piauí (PI) | C814: 2802 | D814: 2759 | E814: 2670 | F814: 2620 | G814: 2571 | H814: =(I814+G814)/2 -> 3146 | I814: 3721 | J814: 3802 | K814: =(L814+J814)/2 -> 3600.5 | L814: 3399 | M814: 3434 | N814: 3460 | O814: 3479 | P814: 3308 | Q814: 3321 | R814: 3333 | S814: 3375 | T814: 3389 | U814: 3404 | V814: 3416
A815: 2207405 | B815: Palmeira do Piauí (PI) | C815: 5358 | D815: 5431 | E815: 5586 | F815: 5671 | G815: 5756 | H815: =(I815+G815)/2 -> 5442 | I815: 5128 | J815: 5116 | K815: =(L815+J815)/2 -> 5047 | L815: 4978 | M815: 4962 | N815: 4997 | O815: 4988 | P815: 4980 | Q815: 4973 | R815: 4967 | S815: 5051 | T815: 5043 | U815: 5036 | V815: 5029
A816: 2207504 | B816: Palmeirais (PI) | C816: 12346 | D816: 12435 | E816: 12622 | F816: 12725 | G816: 12828 | H816: =(I816+G816)/2 -> 13472.5 | I816: 14117 | J816: 14306 | K816: =(L816+J816)/2 -> 14087 | L816: 13868 | M816: 13986 | N816: 14090 | O816: 14151 | P816: 14206 | Q816: 14253 | R816: 14295 | S816: 14488 | T816: 14539 | U816: 14587 | V816: 14633
A817: 2207553 | B817: Paquetá (PI) | C817: 4399 | D817: 4404 | E817: 4417 | F817: 4424 | G817: 4430 | H817: =(I817+G817)/2 -> 4546 | I817: 4662 | J817: 4686 | K817: =(L817+J817)/2 -> 4297 | L817: 3908 | M817: 3891 | N817: 3919 | O817: 3909 | P817: 3900 | Q817: 3893 | R817: 3886 | S817: 3953 | T817: 3945 | U817: 3937 | V817: 3931
... A4504: 4212601 | B4504: Peritiba (SC) | C4504: 3239 | D4504: 3243 | E4504: 3251 | F4504: 3256 | G4504: 3260 | H4504: =(I4504+G4504)/2 -> 3131.5 | I4504: 3003 | J4504: 2977 | K4504: =(L4504+J4504)/2 -> 2973.5 | L4504: 2970 | M4504: 2952 | N4504: 2958 | O4504: 2931 | P4504: 2906 | Q4504: 2880 | R4504: 2855 | S4504: 2814 | T4504: 2787 | U4504: 2760 | V4504: 2733
A4505: 4212650 | B4505: Pescaria Brava (SC) | C4505: ... | D4505: ... | E4505: ... | F4505: ... | G4505: ... | H4505: =(I4505+G4505)/2 -> #VALUE! | I4505: ... | J4505: ... | K4505: =(L4505+J4505)/2 -> #VALUE! | L4505: ... | M4505: 9416 | N4505: 9687 | O4505: 9761 | P4505: 9835 | Q4505: 9908 | R4505: 9980 | S4505: 10022 | T4505: 10091 | U4505: 10159 | V4505: 10225
A4506: 4212700 | B4506: Petrolândia (SC) | C4506: 6267 | D4506: 6202 | E4506: 6067 | F4506: 5992 | G4506: 5917 | H4506: =(I4506+G4506)/2 -> 6065 | I4506: 6213 | J4506: 6188 | K4506: =(L4506+J4506)/2 -> 6149 | L4506: 6110 | M4506: 6090 | N4506: 6140 | O4506: 6110 | P4506: 6080 | Q4506: 6051 | R4506: 6021 | S4506: 5971 | T4506: 5937 | U4506: 5905 | V4506: 5873
A4507: 4212809 | B4507: Balneário Piçarras (SC) | C4507: 11537 | D4507: 11828 | E4507: 12438 | F4507: 12775 | G4507: 13111 | H4507: =(I4507+G4507)/2 -> 13800.5 | I4507: 14490 | J4507: 14845 | K4507: =(L4507+J4507)/2 -> 16198.5 | L4507: 17552 | M4507: 18010 | N4507: 19329 | O4507: 19976 | P4507: 20617 | Q4507: 21253 | R4507: 21884 | S4507: 22511 | T4507: 23147 | U4507: 23772 | V4507: 24385
A4508: 4212908 | B4508: Pinhalzinho (SC) | C4508: 12710 | D4508: 12874 | E4508: 13219 | F4508: 13410 | G4508: 13600 | H4508: =(I4508+G4508)/2 -> 14497 | I4508: 15394 | J4508: 15692 | K4508: =(L4508+J4508)/2 -> 16165 | L4508: 16638 | M4508: 16933 | N4508: 17868 | O4508: 18284 | P4508: 18696 | Q4508: 19105 | R4508: 19511 | S4508: 19906 | T4508: 20313 | U4508: 20712 | V4508: 21103
A4509: 4213005 | B4509: Pinheiro Preto (SC) | C4509: 2804 | D4509: 2838 | E4509: 2911 | F4509: 2951 | G4509: 2991 | H4509: =(I4509+G4509)/2 -> 3006 | I4509: 3021 | J4509: 3048 | K4509: =(L4509+J4509)/2 -> 3114 | L4509: 3180 | M4509: 3190 | N4509: 3310 | O4509: 3353 | P4509: 3396 | Q4509: 3438 | R4509: 3480 | S4509: 3513 | T4509: 3555 | U4509: 3596 | V4509: 3635
A4510: 4213104 | B4510: Piratuba (SC) | C4510: 6002 | D4510: 6090 | E4510: 6275 | F4510: 6378 | G4510: 6479 | H4510: =(I4510+G4510)/2 -> 5528 | I4510: 4577 | J4510: 4446 | K4510: =(L4510+J4510)/2 -> 4577 | L4510: 4708 | M4510: 4632 | N4510: 4533 | O4510: 4424 | P4510: 4316 | Q4510: 4209 | R4510: 4102 | S4510: 3965 | T4510: 3854 | U4510: 3745 | V4510: 3637
A4511: 4213153 | B4511: Planalto Alegre (SC) | C4511: 2428 | D4511: 2417 | E4511: 2394 | F4511: 2381 | G4511: 2368 | H4511: =(I4511+G4511)/2 -> 2554 | I4511: 2740 | J4511: 2767 | K4511: =(L4511+J4511)/2 -> 2718.5 | L4511: 2670 | M4511: 2685 | N4511: 2761 | O4511: 2782 | P4511: 2803 | Q4511: 2823 | R4511: 2844 | S4511: 2850 | T4511: 2870 | U4511: 2888 | V4511: 2907
A4512: 4213203 | B4512: Pomerode (SC) | C4512: 22833 | D4512: 23161 | E4512: 23849 | F4512: 24230 | G4512: 24607 | H4512: =(I4512+G4512)/2 -> 25491 | I4512: 26375 | J4512: 26788 | K4512: =(L4512+J4512)/2 -> 27490 | L4512: 28192 | M4512: 28610 | N4512: 30009 | O4512: 30598 | P4512: 31181 | Q4512: 31760 | R4512: 32334 | S4512: 32874 | T4512: 33447 | U4512: 34010 | V4512: 34561
A4513: 4213302 | B4513: Ponte Alta (SC) | C4513: 5256 | D4513: 5296 | E4513: 5381 | F4513: 5429 | G4513: 5475 | H4513: =(I4513+G4513)/2 -> 5350.5 | I4513: 5226 | J4513: 5228 | K4513: =(L4513+J4513)/2 -> 5050.5 | L4513: 4873 | M4513: 4853 | N4513: 4885 | O4513: 4855 | P4513: 4825 | Q4513: 4796 | R4513: 4767 | S4513: 4714 | T4513: 4682 | U4513: 4650 | V4513: 4619
A4514: 4213351 | B4514: Ponte Alta do Norte (SC) | C4514: 3348 | D4514: 3407 | E4514: 3531 | F4514: 3600 | G4514: 3668 | H4514: =(I4514+G4514)/2 -> 3652.5 | I4514: 3637 | J4514: 3677 | K4514: =(L4514+J4514)/2 -> 3493.5 | L4514: 3310 | M4514: 3316 | N4514: 3381 | O4514: 3389 | P4514: 3397 | Q4514: 3405 | R4514: 3413 | S4514: 3408 | T4514: 3414 | U4514: 3420 | V4514: 3426
A4515: 4213401 | B4515: Ponte Serrada (SC) | C4515: 10882 | D4515: 11031 | E4515: 11344 | F4515: 11518 | G4515: 11690 | H4515: =(I4515+G4515)/2 -> 11657.5 | I4515: 11625 | J4515: 11724 | K4515: =(L4515+J4515)/2 -> 11396 | L4515: 11068 | M4515: 11102 | N4515: 11358 | O4515: 11405 | P4515: 11452 | Q4515: 11499 | R4515: 11545 | S4515: 11552 | T4515: 11593 | U4515: 11634 | V4515: 11674
A4516: 4213500 | B4516: Porto Belo (SC) | C4516: 11493 | D4516: 11859 | E4516: 12627 | F4516: 13053 | G4516: 13475 | H4516: =(I4516+G4516)/2 -> 13692.5 | I4516: 13910 | J4516: 14228 | K4516: =(L4516+J4516)/2 -> 15362 | L4516: 16496 | M4516: 16896 | N4516: 18066 | O4516: 18630 | P4516: 19189 | Q4516: 19744 | R4516: 20294 | S4516: 20834 | T4516: 21388 | U4516: 21932 | V4516: 22466
A4517: 4213609 | B4517: Porto União (SC) | C4517: 32274 | D4517: 32466 | E4517: 32871 | F4517: 33095 | G4517: 33318 | H4517: =(I4517+G4517)/2 -> 33304 | I4517: 33290 | J4517: 33408 | K4517: =(L4517+J4517)/2 -> 33513.5 | L4517: 33619 | M4517: 33740 | N4517: 34551 | O4517: 34717 | P4517: 34882 | Q4517: 35045 | R4517: 35207 | S4517: 35250 | T4517: 35398 | U4517: 35543 | V4517: 35685
... A4606: 4219853 | B4606: Zortéa (SC) | C4606: 2703 | D4606: 2736 | E4606: 2804 | F4606: 2842 | G4606: 2879 | H4606: =(I4606+G4606)/2 -> 2930 | I4606: 2981 | J4606: 3015 | K4606: =(L4606+J4606)/2 -> 3017 | L4606: 3019 | M4606: 3046 | N4606: 3153 | O4606: 3190 | P4606: 3227 | Q4606: 3264 | R4606: 3300 | S4606: 3328 | T4606: 3363 | U4606: 3398 | V4606: 3432
A4607: 4220000 | B4607: Balneário Rincão (SC) | C4607: ... | D4607: ... | E4607: ... | F4607: ... | G4607: ... | H4607: =(I4607+G4607)/2 -> #VALUE! | I4607: ... | J4607: ... | K4607: =(L4607+J4607)/2 -> #VALUE! | L4607: ... | M4607: 11136 | N4607: 11628 | O4607: 11824 | P4607: 12018 | Q4607: 12212 | R4607: 12403 | S4607: 12570 | T4607: 12760 | U4607: 12946 | V4607: 13129
A4608: 4300034 | B4608: Aceguá (RS) | C4608: 4002 | D4608: 4036 | E4608: 4109 | F4608: 4149 | G4608: 4188 | H4608: =(I4608+G4608)/2 -> 4250 | I4608: 4312 | J4608: 4347 | K4608: =(L4608+J4608)/2 -> 4388.5 | L4608: 4430 | M4608: 4465 | N4608: 4638 | O4608: 4671 | P4608: 4702 | Q4608: 4731 | R4608: 4759 | S4608: 4858 | T4608: 4901 | U4608: 4942 | V4608: 4981
A4609: 4300059 | B4609: Água Santa (RS) | C4609: 3852 | D4609: 3880 | E4609: 3940 | F4609: 3973 | G4609: 4006 | H4609: =(I4609+G4609)/2 -> 3822 | I4609: 3638 | J4609: 3619 | K4609: =(L4609+J4609)/2 -> 3668 | L4609: 3717 | M4609: 3712 | N4609: 3838 | O4609: 3839 | P4609: 3840 | Q4609: 3841 | R4609: 3841 | S4609: 3753 | T4609: 3748 | U4609: 3743 | V4609: 3738
A4610: 4300109 | B4610: Agudo (RS) | C4610: 17610 | D4610: 17682 | E4610: 17833 | F4610: 17917 | G4610: 18000 | H4610: =(I4610+G4610)/2 -> 17557 | I4610: 17114 | J4610: 17063 | K4610: =(L4610+J4610)/2 -> 16864.5 | L4610: 16666 | M4610: 16612 | N4610: 17161 | O4610: 17140 | P4610: 17120 | Q4610: 17102 | R4610: 17085 | S4610: 16524 | T4610: 16461 | U4610: 16401 | V4610: 16344
A4611: 4300208 | B4611: Ajuricaba (RS) | C4611: 7627 | D4611: 7588 | E4611: 7508 | F4611: 7463 | G4611: 7419 | H4611: =(I4611+G4611)/2 -> 7415 | I4611: 7411 | J4611: 7374 | K4611: =(L4611+J4611)/2 -> 7297.5 | L4611: 7221 | M4611: 7187 | N4611: 7420 | O4611: 7403 | P4611: 7387 | Q4611: 7372 | R4611: 7358 | S4611: 7063 | T4611: 7024 | U4611: 6987 | V4611: 6951
A4612: 4300307 | B4612: Alecrim (RS) | C4612: 8144 | D4612: 7984 | E4612: 7650 | F4612: 7465 | G4612: 7281 | H4612: =(I4612+G4612)/2 -> 7330.5 | I4612: 7380 | J4612: 7259 | K4612: =(L4612+J4612)/2 -> 7097 | L4612: 6935 | M4612: 6828 | N4612: 7010 | O4612: 6935 | P4612: 6865 | Q4612: 6799 | R4612: 6736 | S4612: 6077 | T4612: 5950 | U4612: 5827 | V4612: 5710
A4613: 4300406 | B4613: Alegrete (RS) | C4613: 85527 | D4613: 86078 | E4613: 87236 | F4613: 87877 | G4613: 88513 | H4613: =(I4613+G4613)/2 -> 84030.5 | I4613: 79548 | J4613: 78984 | K4613: =(L4613+J4613)/2 -> 78062 | L4613: 77140 | M4613: 76644 | N4613: 79054 | O4613: 78768 | P4613: 78499 | Q4613: 78244 | R4613: 78003 | S4613: 74173 | T4613: 73589 | U4613: 73028 | V4613: 72493
A4614: 4300455 | B4614: Alegria (RS) | C4614: 5182 | D4614: 5096 | E4614: 4916 | F4614: 4816 | G4614: 4717 | H4614: =(I4614+G4614)/2 -> 4775.5 | I4614: 4834 | J4614: 4775 | K4614: =(L4614+J4614)/2 -> 4497.5 | L4614: 4220 | M4614: 4141 | N4614: 4244 | O4614: 4188 | P4614: 4135 | Q4614: 4085 | R4614: 4037 | S4614: 3559 | T4614: 3464 | U4614: 3374 | V4614: 3287
A4615: 4300471 | B4615: Almirante Tamandaré do Sul (RS) | C4615: 2288 | D4615: 2310 | E4615: 2357 | F4615: 2383 | G4615: 2408 | H4615: =(I4615+G4615)/2 -> 2310 | I4615: 2212 | J4615: 2208 | K4615: =(L4615+J4615)/2 -> 2131 | L4615: 2054 | M4615: 2041 | N4615: 2106 | O4615: 2098 | P4615: 2091 | Q4615: 2085 | R4615: 2079 | S4615: 1979 | T4615: 1964 | U4615: 1949 | V4615: 1935
A4616: 4300505 | B4616: Alpestre (RS) | C4616: 9571 | D4616: 9249 | E4616: 8572 | F4616: 8198 | G4616: 7826 | H4616: =(I4616+G4616)/2 -> 8421.5 | I4616: 9017 | J4616: 8880 | K4616: =(L4616+J4616)/2 -> 8368 | L4616: 7856 | M4616: 7689 | N4616: 7871 | O4616: 7752 | P4616: 7640 | Q4616: 7533 | R4616: 7433 | S4616: 6458 | T4616: 6258 | U4616: 6067 | V4616: 5885
A4617: 4300554 | B4617: Alto Alegre (RS) | C4617: 2137 | D4617: 2136 | E4617: 2136 | F4617: 2136 | G4617: 2136 | H4617: =(I4617+G4617)/2 -> 2050.5 | I4617: 1965 | J4617: 1945 | K4617: =(L4617+J4617)/2 -> 1885.5 | L4617: 1826 | M4617: 1805 | N4617: 1856 | O4617: 1841 | P4617: 1828 | Q4617: 1815 | R4617: 1803 | S4617: 1663 | T4617: 1638 | U4617: 1613 | V4617: 1590
A4618: 4300570 | B4618: Alto Feliz (RS) | C4618: 2844 | D4618: 2849 | E4618: 2859 | F4618: 2864 | G4618: 2869 | H4618: =(I4618+G4618)/2 -> 2958.5 | I4618: 3048 | J4618: 3067 | K4618: =(L4618+J4618)/2 -> 2995.5 | L4618: 2924 | M4618: 2930 | N4618: 3035 | O4618: 3017 | P4618: 3025 | Q4618: 3032 | R4618: 3040 | S4618: 3020 | T4618: 3028 | U4618: 3036 | V4618: 3043
A4619: 4300604 | B4619: Alvorada (RS) | C4619: 192789 | D4619: 196882 | E4619: 205476 | F4619: 210233 | G4619: 214953 | H4619: =(I4619+G4619)/2 -> 213114.5 | I4619: 211276 | J4619: 213894 | K4619: =(L4619+J4619)/2 -> 205233 | L4619: 196572 | M4619: 197441 | N4619: 204750 | O4619: 205683 | P4619: 206561 | Q4619: 207392 | R4619: 208177 | S4619: 209213 | T4619: 210305 | U4619: 211352 | V4619: 212352
... A4924: 4314506 | B4924: Pinheiro Machado (RS) | C4924: 13954 | D4924: 14074 | E4924: 14327 | F4924: 14467 | G4924: 14606 | H4924: =(I4924+G4924)/2 -> 13909.5 | I4924: 13213 | J4924: 13152 | K4924: =(L4924+J4924)/2 -> 12931 | L4924: 12710 | M4924: 12642 | N4924: 13047 | O4924: 13011 | P4924: 12976 | Q4924: 12944 | R4924: 12913 | S4924: 12351 | T4924: 12271 | U4924: 12195 | V4924: 12122
A4925: 4314548 | B4925: Pinto Bandeira (RS) | C4925: ... | D4925: ... | E4925: ... | F4925: ... | G4925: ... | H4925: =(I4925+G4925)/2 -> #VALUE! | I4925: ... | J4925: ... | K4925: =(L4925+J4925)/2 -> #VALUE! | L4925: ... | M4925: 2578 | N4925: 2681 | O4925: 2800 | P4925: 2824 | Q4925: 2847 | R4925: 2868 | S4925: 2968 | T4925: 3003 | U4925: 3036 | V4925: 3068
A4926: 4314555 | B4926: Pirapó (RS) | C4926: 3250 | D4926: 3204 | E4926: 3108 | F4926: 3055 | G4926: 3002 | H4926: =(I4926+G4926)/2 -> 3009 | I4926: 3016 | J4926: 2979 | K4926: =(L4926+J4926)/2 -> 2845.5 | L4926: 2712 | M4926: 2668 | N4926: 2738 | O4926: 2707 | P4926: 2678 | Q4926: 2651 | R4926: 2625 | S4926: 2357 | T4926: 2304 | U4926: 2254 | V4926: 2205
A4927: 4314605 | B4927: Piratini (RS) | C4927: 19784 | D4927: 19956 | E4927: 20316 | F4927: 20516 | G4927: 20714 | H4927: =(I4927+G4927)/2 -> 20873.5 | I4927: 21033 | J4927: 21180 | K4927: =(L4927+J4927)/2 -> 20527 | L4927: 19874 | M4927: 19906 | N4927: 20614 | O4927: 20664 | P4927: 20712 | Q4927: 20757 | R4927: 20799 | S4927: 20621 | T4927: 20663 | U4927: 20704 | V4927: 20743
A4928: 4314704 | B4928: Planalto (RS) | C4928: 11089 | D4928: 10990 | E4928: 10782 | F4928: 10667 | G4928: 10553 | H4928: =(I4928+G4928)/2 -> 10674.5 | I4928: 10796 | J4928: 10734 | K4928: =(L4928+J4928)/2 -> 10599.5 | L4928: 10465 | M4928: 10407 | N4928: 10739 | O4928: 10707 | P4928: 10678 | Q4928: 10650 | R4928: 10623 | S4928: 10152 | T4928: 10084 | U4928: 10019 | V4928: 9957
A4929: 4314753 | B4929: Poço das Antas (RS) | C4929: 1912 | D4929: 1897 | E4929: 1864 | F4929: 1846 | G4929: 1828 | H4929: =(I4929+G4929)/2 -> 1954.5 | I4929: 2081 | J4929: 2098 | K4929: =(L4929+J4929)/2 -> 2059 | L4929: 2020 | M4929: 2023 | N4929: 2094 | O4929: 2099 | P4929: 2104 | Q4929: 2108 | R4929: 2112 | S4929: 2094 | T4929: 2098 | U4929: 2101 | V4929: 2105
A4930: 4314779 | B4930: Pontão (RS) | C4930: 3786 | D4930: 3732 | E4930: 3617 | F4930: 3554 | G4930: 3491 | H4930: =(I4930+G4930)/2 -> 3761 | I4930: 4031 | J4930: 4040 | K4930: =(L4930+J4930)/2 -> 3947 | L4930: 3854 | M4930: 3850 | N4930: 3982 | O4930: 3984 | P4930: 3986 | Q4930: 3988 | R4930: 3990 | S4930: 3908 | T4930: 3904 | U4930: 3901 | V4930: 3898
A4931: 4314787 | B4931: Ponte Preta (RS) | C4931: 2010 | D4931: 2002 | E4931: 1985 | F4931: 1975 | G4931: 1965 | H4931: =(I4931+G4931)/2 -> 1914.5 | I4931: 1864 | J4931: 1846 | K4931: =(L4931+J4931)/2 -> 1787.5 | L4931: 1729 | M4931: 1709 | N4931: 1757 | O4931: 1743 | P4931: 1730 | Q4931: 1717 | R4931: 1706 | S4931: 1572 | T4931: 1547 | U4931: 1524 | V4931: 1501
A4932: 4314803 | B4932: Portão (RS) | C4932: 25744 | D4932: 26249 | E4932: 27308 | F4932: 27895 | G4932: 28477 | H4932: =(I4932+G4932)/2 -> 29365.5 | I4932: 30254 | J4932: 30802 | K4932: =(L4932+J4932)/2 -> 31101.5 | L4932: 31401 | M4932: 31866 | N4932: 33212 | O4932: 33615 | P4932: 33994 | Q4932: 34353 | R4932: 34692 | S4932: 36510 | T4932: 37079 | U4932: 37561 | V4932: 38081
A4933: 4314902 | B4933: Porto Alegre (RS) | C4933: 1383454 | D4933: 1394085 | E4933: 1416363 | F4933: 1428696 | G4933: 1440939 | H4933: =(I4933+G4933)/2 -> 1435587 | I4933: 1430235 | J4933: 1436123 | K4933: =(L4933+J4933)/2 -> 1424608.5 | L4933: 1413094 | M4933: 1416714 | N4933: 1467816 | O4933: 1472482 | P4933: 1476867 | Q4933: 1481019 | R4933: 1484941 | S4933: 1479101 | T4933: 1483771 | U4933: 1488252 | V4933: 1492530
A4934: 4315008 | B4934: Porto Lucena (RS) | C4934: 6249 | D4934: 6180 | E4934: 6035 | F4934: 5954 | G4934: 5875 | H4934: =(I4934+G4934)/2 -> 5771 | I4934: 5667 | J4934: 5587 | K4934: =(L4934+J4934)/2 -> 5462.5 | L4934: 5338 | M4934: 5265 | N4934: 5410 | O4934: 5360 | P4934: 5313 | Q4934: 5269 | R4934: 5227 | S4934: 4765 | T4934: 4678 | U4934: 4594 | V4934: 4514
A4935: 4315057 | B4935: Porto Mauá (RS) | C4935: 2770 | D4935: 2755 | E4935: 2724 | F4935: 2707 | G4935: 2690 | H4935: =(I4935+G4935)/2 -> 2646 | I4935: 2602 | J4935: 2580 | K4935: =(L4935+J4935)/2 -> 2551.5 | L4935: 2523 | M4935: 2503 | N4935: 2579 | O4935: 2568 | P4935: 2557 | Q4935: 2546 | R4935: 2536 | S4935: 2397 | T4935: 2374 | U4935: 2352 | V4935: 2332
A4936: 4315073 | B4936: Porto Vera Cruz (RS) | C4936: 2383 | D4936: 2345 | E4936: 2266 | F4936: 2223 | G4936: 2179 | H4936: =(I4936+G4936)/2 -> 2129.5 | I4936: 2080 | J4936: 2038 | K4936: =(L4936+J4936)/2 -> 1922 | L4936: 1806 | M4936: 1760 | N4936: 1797 | O4936: 1764 | P4936: 1733 | Q4936: 1704 | R4936: 1676 | S4936: 1415 | T4936: 1360 | U4936: 1308 | V4936: 1258
A4937: 4315107 | B4937: Porto Xavier (RS) | C4937: 11244 | D4937: 11269 | E4937: 11321 | F4937: 11350 | G4937: 11379 | H4937: =(I4937+G4937)/2 -> 11262 | I4937: 11145 | J4937: 11131 | K4937: =(L4937+J4937)/2 -> 10820.5 | L4937: 10510 | M4937: 10463 | N4937: 10802 | O4937: 10779 | P4937: 10758 | Q4937: 10737 | R4937: 10718 | S4937: 10301 | T4937: 10246 | U4937: 10194 | V4937: 10144
... A5138: 5003801 | B5138: Fátima do Sul (MS) | C5138: 18471 | D5138: 18173 | E5138: 17549 | F5138: 17204 | G5138: 16861 | H5138: =(I5138+G5138)/2 -> 18094 | I5138: 19327 | J5138: 19332 | K5138: =(L5138+J5138)/2 -> 19181 | L5138: 19030 | M5138: 19024 | N5138: 19260 | O5138: 19240 | P5138: 19220 | Q5138: 19200 | R5138: 19181 | S5138: 19234 | T5138: 19189 | U5138: 19170 | V5138: 19152
A5139: 5003900 | B5139: Figueirão (MS) | C5139: ... | D5139: ... | E5139: 2908 | F5139: 2927 | G5139: 2945 | H5139: =(I5139+G5139)/2 -> 3166.5 | I5139: 3388 | J5139: 3443 | K5139: =(L5139+J5139)/2 -> 3190 | L5139: 2937 | M5139: 2945 | N5139: 2997 | O5139: 3005 | P5139: 3012 | Q5139: 3020 | R5139: 3027 | S5139: 3044 | T5139: 3051 | U5139: 3059 | V5139: 3066
A5140: 5004007 | B5140: Glória de Dourados (MS) | C5140: 9645 | D5140: 9464 | E5140: 9084 | F5140: 8873 | G5140: 8665 | H5140: =(I5140+G5140)/2 -> 9290 | I5140: 9915 | J5140: 9894 | K5140: =(L5140+J5140)/2 -> 9906.5 | L5140: 9919 | M5140: 9911 | N5140: 10025 | O5140: 10008 | P5140: 9992 | Q5140: 9976 | R5140: 9960 | S5140: 9981 | T5140: 9965 | U5140: 9950 | V5140: 9934
...

Sheet Tabela_2
A1: Cód. | B1: Município | C1: 2003 | D1: 2004 | E1: 2005 | F1: 2006 | G1: 2007 | H1: 2008 | I1: 2009 | J1: 2010 | K1: 2011 | L1: 2012 | M1: 2013 | N1: 2014 | O1: 2015 | P1: 2016 | Q1: 2017 | R1: 2018 | S1: 2019 | T1: 2020 | U1: 2021
A2: 1100015 | B2: Alta Floresta D'Oeste (RO) | C2: =(Tabela!D2-Tabela!C2)/Tabela!C2 -> 0.011969013 | D2: =(Tabela!E2-Tabela!D2)/Tabela!D2 -> 0.052171389 | E2: =(Tabela!F2-Tabela!E2)/Tabela!E2 -> -0.012827144 | F2: =(Tabela!G2-Tabela!F2)/Tabela!F2 -> 0.013133536 | G2: =(Tabela!H2-Tabela!G2)/Tabela!G2 -> -0.076331667 | H2: =(Tabela!I2-Tabela!H2)/Tabela!H2 -> -0.082639692 | I2: =(Tabela!J2-Tabela!I2)/Tabela!I2 -> -0.009073524 | J2: =(Tabela!K2-Tabela!J2)/Tabela!J2 -> -0.0025868441 | ... U2: =(Tabela!V2-Tabela!U2)/Tabela!U2 -> -0.0093277015
A3: 1100023 | B3: Ariquemes (RO) | C3: =(Tabela!D3-Tabela!C3)/Tabela!C3 -> 0.021027948 | D3: =(Tabela!E3-Tabela!D3)/Tabela!D3 -> 0.090625 | E3: =(Tabela!F3-Tabela!E3)/Tabela!E3 -> -0.02151874 | F3: =(Tabela!G3-Tabela!F3)/Tabela!F3 -> 0.022262469 | G3: =(Tabela!H3-Tabela!G3)/Tabela!G3 -> -0.013477291 | H3: =(Tabela!I3-Tabela!H3)/Tabela!H3 -> -0.013661409 | I3: =(Tabela!J3-Tabela!I3)/Tabela!I3 -> 0.011350067 | J3: =(Tabela!K3-Tabela!J3)/Tabela!J3 -> 0.035240411 | ... U3: =(Tabela!V3-Tabela!U3)/Tabela!U3 -> 0.014837066
A4: 1100031 | B4: Cabixi (RO) | C4: =(Tabela!D4-Tabela!C4)/Tabela!C4 -> -0.0016021362 | D4: =(Tabela!E4-Tabela!D4)/Tabela!D4 -> -0.0076223589 | E4: =(Tabela!F4-Tabela!E4)/Tabela!E4 -> 0.0020212909 | F4: =(Tabela!G4-Tabela!F4)/Tabela!F4 -> -0.0020172136 | G4: =(Tabela!H4-Tabela!G4)/Tabela!G4 -> -0.043390379 | H4: =(Tabela!I4-Tabela!H4)/Tabela!H4 -> -0.045358501 | I4: =(Tabela!J4-Tabela!I4)/Tabela!I4 -> -0.012099749 | J4: =(Tabela!K4-Tabela!J4)/Tabela!J4 -> -0.035399552 | ... U4: =(Tabela!V4-Tabela!U4)/Tabela!U4 -> -0.023323053
A5: 1100049 | B5: Cacoal (RO) | C5: =(Tabela!D5-Tabela!C5)/Tabela!C5 -> 0.0050684987 | D5: =(Tabela!E5-Tabela!D5)/Tabela!D5 -> 0.022191605 | E5: =(Tabela!F5-Tabela!E5)/Tabela!E5 -> -0.0056139341 | F5: =(Tabela!G5-Tabela!F5)/Tabela!F5 -> 0.0057114281 | G5: =(Tabela!H5-Tabela!G5)/Tabela!G5 -> 0.012044961 | H5: =(Tabela!I5-Tabela!H5)/Tabela!H5 -> 0.011901606 | I5: =(Tabela!J5-Tabela!I5)/Tabela!I5 -> 0.0052643011 | J5: =(Tabela!K5-Tabela!J5)/Tabela!J5 -> 0.0018048935 | ... U5: =(Tabela!V5-Tabela!U5)/Tabela!U5 -> 0.0060889712
A6: 1100056 | B6: Cerejeiras (RO) | C6: =(Tabela!D6-Tabela!C6)/Tabela!C6 -> -0.0073082287 | D6: =(Tabela!E6-Tabela!D6)/Tabela!D6 -> -0.032426661 | E6: =(Tabela!F6-Tabela!E6)/Tabela!E6 -> 0.0086542371 | F6: =(Tabela!G6-Tabela!F6)/Tabela!F6 -> -0.0086951514 | G6: =(Tabela!H6-Tabela!G6)/Tabela!G6 -> -0.012518153 | H6: =(Tabela!I6-Tabela!H6)/Tabela!H6 -> -0.012676843 | I6: =(Tabela!J6-Tabela!I6)/Tabela!I6 -> -0.0096520496 | J6: =(Tabela!K6-Tabela!J6)/Tabela!J6 -> 0.0095355553 | ... U6: =(Tabela!V6-Tabela!U6)/Tabela!U6 -> -0.0071587262
A7: 1100064 | B7: Colorado do Oeste (RO) | C7: =(Tabela!D7-Tabela!C7)/Tabela!C7 -> -0.02246061 | D7: =(Tabela!E7-Tabela!D7)/Tabela!D7 -> -0.101068 | E7: =(Tabela!F7-Tabela!E7)/Tabela!E7 -> 0.029102403 | F7: =(Tabela!G7-Tabela!F7)/Tabela!F7 -> -0.028650109 | G7: =(Tabela!H7-Tabela!G7)/Tabela!G7 -> -0.0034347399 | H7: =(Tabela!I7-Tabela!H7)/Tabela!H7 -> -0.003446578 | I7: =(Tabela!J7-Tabela!I7)/Tabela!I7 -> -0.021629337 | J7: =(Tabela!K7-Tabela!J7)/Tabela!J7 -> 0.01447649 | ... U7: =(Tabela!V7-Tabela!U7)/Tabela!U7 -> -0.02129439
A8: 1100072 | B8: Corumbiara (RO) | C8: =(Tabela!D8-Tabela!C8)/Tabela!C8 -> -0.013582677 | D8: =(Tabela!E8-Tabela!D8)/Tabela!D8 -> -0.060965875 | E8: =(Tabela!F8-Tabela!E8)/Tabela!E8 -> 0.016788864 | F8: =(Tabela!G8-Tabela!F8)/Tabela!F8 -> -0.01672066 | G8: =(Tabela!H8-Tabela!G8)/Tabela!G8 -> 0.018705495 | H8: =(Tabela!I8-Tabela!H8)/Tabela!H8 -> 0.018362024 | I8: =(Tabela!J8-Tabela!I8)/Tabela!I8 -> -0.0082983301 | J8: =(Tabela!K8-Tabela!J8)/Tabela!J8 -> -0.052944215 | ... U8: =(Tabela!V8-Tabela!U8)/Tabela!U8 -> -0.023268698
A9: 1100080 | B9: Costa Marques (RO) | C9: =(Tabela!D9-Tabela!C9)/Tabela!C9 -> 0.033874382 | D9: =(Tabela!E9-Tabela!D9)/Tabela!D9 -> 0.14392979 | E9: =(Tabela!F9-Tabela!E9)/Tabela!E9 -> -0.032563294 | F9: =(Tabela!G9-Tabela!F9)/Tabela!F9 -> 0.034011807 | G9: =(Tabela!H9-Tabela!G9)/Tabela!G9 -> 0.095355773 | H9: =(Tabela!I9-Tabela!H9)/Tabela!H9 -> 0.087054613 | I9: =(Tabela!J9-Tabela!I9)/Tabela!I9 -> 0.034280398 | J9: =(Tabela!K9-Tabela!J9)/Tabela!J9 -> -0.014842236 | ... U9: =(Tabela!V9-Tabela!U9)/Tabela!U9 -> 0.024311097
A10: 1100098 | B10: Espigão D'Oeste (RO) | C10: =(Tabela!D10-Tabela!C10)/Tabela!C10 -> 0.0094199306 | D10: =(Tabela!E10-Tabela!D10)/Tabela!D10 -> 0.041106241 | E10: =(Tabela!F10-Tabela!E10)/Tabela!E10 -> -0.010233706 | F10: =(Tabela!G10-Tabela!F10)/Tabela!F10 -> 0.010449512 | G10: =(Tabela!H10-Tabela!G10)/Tabela!G10 -> 0.019195181 | H10: =(Tabela!I10-Tabela!H10)/Tabela!H10 -> 0.018833666 | I10: =(Tabela!J10-Tabela!I10)/Tabela!I10 -> 0.0096096726 | J10: =(Tabela!K10-Tabela!J10)/Tabela!J10 -> 0.0012287138 | ... U10: =(Tabela!V10-Tabela!U10)/Tabela!U10 -> 0.009603915
A11: 1100106 | B11: Guajará-Mirim (RO) | C11: =(Tabela!D11-Tabela!C11)/Tabela!C11 -> 0.013624534 | D11: =(Tabela!E11-Tabela!D11)/Tabela!D11 -> 0.059076722 | E11: =(Tabela!F11-Tabela!E11)/Tabela!E11 -> -0.014450386 | F11: =(Tabela!G11-Tabela!F11)/Tabela!F11 -> 0.01483107 | G11: =(Tabela!H11-Tabela!G11)/Tabela!G11 -> -0.018309491 | H11: =(Tabela!I11-Tabela!H11)/Tabela!H11 -> -0.018650981 | I11: =(Tabela!J11-Tabela!I11)/Tabela!I11 -> 0.0054512716 | J11: =(Tabela!K11-Tabela!J11)/Tabela!J11 -> 0.014376135 | ... U11: =(Tabela!V11-Tabela!U11)/Tabela!U11 -> 0.0080333362
A12: 1100114 | B12: Jaru (RO) | C12: =(Tabela!D12-Tabela!C12)/Tabela!C12 -> 0.0064211069 | D12: =(Tabela!E12-Tabela!D12)/Tabela!D12 -> 0.028098207 | E12: =(Tabela!F12-Tabela!E12)/Tabela!E12 -> -0.0070770653 | F12: =(Tabela!G12-Tabela!F12)/Tabela!F12 -> 0.0071991404 | G12: =(Tabela!H12-Tabela!G12)/Tabela!G12 -> -0.020331781 | H12: =(Tabela!I12-Tabela!H12)/Tabela!H12 -> -0.020753741 | I12: =(Tabela!J12-Tabela!I12)/Tabela!I12 -> -0.00022240756 | J12: =(Tabela!K12-Tabela!J12)/Tabela!J12 -> -0.019094229 | ... U12: =(Tabela!V12-Tabela!U12)/Tabela!U12 -> -0.0029252228
A13: 1100122 | B13: Ji-Paraná (RO) | C13: =(Tabela!D13-Tabela!C13)/Tabela!C13 -> 0.0080869229 | D13: =(Tabela!E13-Tabela!D13)/Tabela!D13 -> 0.035300667 | E13: =(Tabela!F13-Tabela!E13)/Tabela!E13 -> -0.0088327853 | F13: =(Tabela!G13-Tabela!F13)/Tabela!F13 -> 0.0090182232 | G13: =(Tabela!H13-Tabela!G13)/Tabela!G13 -> -0.012101928 | H13: =(Tabela!I13-Tabela!H13)/Tabela!H13 -> -0.012250178 | I13: =(Tabela!J13-Tabela!I13)/Tabela!I13 -> 0.0027369543 | J13: =(Tabela!K13-Tabela!J13)/Tabela!J13 -> 0.028614539 | ... U13: =(Tabela!V13-Tabela!U13)/Tabela!U13 -> 0.0078225354
... A5571: 5300108 | B5571: Brasília (DF) | C5571: =(Tabela!D5571-Tabela!C5571)/Tabela!C5571 -> 0.020481499 | D5571: =(Tabela!E5571-Tabela!D5571)/Tabela!D5571 -> 0.042131913 | E5571: =(Tabela!F5571-Tabela!E5571)/Tabela!E5571 -> 0.022374191 | F5571: =(Tabela!G5571-Tabela!F5571)/Tabela!F5571 -> 0.021720383 | G5571: =(Tabela!H5571-Tabela!G5571)/Tabela!G5571 -> 0.036365501 | H5571: =(Tabela!I5571-Tabela!H5571)/Tabela!H5571 -> 0.035089456 | I5571: =(Tabela!J5571-Tabela!I5571)/Tabela!I5571 -> 0.019445799 | J5571: =(Tabela!K5571-Tabela!J5571)/Tabela!J5571 -> 0.00059707275 | ... U5571: =(Tabela!V5571-Tabela!U5571)/Tabela!U5571 -> 0.012822943
A5572: Fonte: IBGE - Estimativas de População

Sheet Notas
A1: Notas
A2: Em 2003: O contingente populacional estimado para o Município de Caraíbas, no Estado da Bahia foi reduzido em 5.006 habitantes, devido ao processo de sindicância recentemente encerrado que apurou sobre enumeração ocorrida quando da realização do Censo Demográfico 2000. Em 2004:
A3: 1 - O contingente populacional estimado para o Município de Caraíbas, no Estado da Bahia foi reduzido em 5.006 habitantes, devido ao processo de sindicância recentemente encerrado que apurou sobre enumeração ocorrida quando da realização do Censo Demográfico 2000.
A4: 2 - Inclusive 4 municípios com instalação prevista para 1º de janeiro de 2005: Aroeiras do Itaim (PI), Figueirão (MS), Ipiranga do Norte (MT) e Itanhangá (MT). Em 2008: Inclusive o Município de Nazária - PI, com previsão de instalação em 1º de janeiro de 2009. Em 2009: Por determinação judicial e para efeito de distribuição do Fundo de Participação dos Municípios, a população do Município de Uruará-PA é de 59.881 habitantes. Processo Judicial nº 2008.39.03.000085-6. Em 2011:
A5: 1 - A população do Brasil difere em 2.791 pessoas (192.379.287 pessoas) em relação àquela divulgada no D.O.U em 31/08/2011 (192.376.496 pessoas) em decorrência do critério de arredondamento para números inteiros, a ser adotado a partir deste ano.
A6: 2 - O Município de Santarém-PB, código 13653, passou a ser denominado oficialmente de Joca Claudino-PB a partir de 23/11/2010, por força de Lei Municipal nº 049/2010.
A7: 3 - o Município de Campo de Santana-PB, código 16409, passou a ser denominado oficialmente de Tacima-PB a partir de 30/12/2009, por força de Lei Complementar nº 016/2009. Em 2012:
A8: 1 - Por determinação judicial e para efeito de distribuição do Fundo de Participação dos Municípios, a população do Município de Brasil Novo-PA é de 17.960 habitantes. Processo Judicial nº 1-28.2012.4.01.3903.
A9: 2 - Por determinação judicial e para efeito de distribuição do Fundo de Participação dos Municípios, a população do Município de Jacareacanga-PA é de 41.487 habitantes. Processo Judicial nº 798-41.2011.4.01.3902, Seção Judiciária de Itaituba-PA.
A10: 3 - Municípios instalados em 1º de janeiro de 2013. Em 2013: Por determinação judicial e para efeito de distribuição do Fundo de Participação dos Municípios, a população do Município de Jacareacanga-PA é de 41.487 habitantes. Processo Judicial nº 798-41.2011 4.01.3902 Seção Judiciária de Itaituba-PA. Em 2014:
A11: 1 - Por determinação judicial e para efeito de distribuição do Fundo de Participação dos Municípios, a população do Município de Jacareacanga-PA é de 41.487 habitantes. Processo Judicial nº 798-41.2011.4.01.3902, Seção Judiciária de Itaituba-PA.
A12: 2 - Por determinação judicial o Município de Coronel João Sá - BA teve os efeitos das estimativas das populações de 2014, 2015 e 2016 suspensas, passando a vigorar, para efeito de distribuição do Fundo de Participação dos Municípios, a população estimada para o ano de 2013, que foi de 17.422 habitantes. Processo Judicial nº 0002222-53.2017.4.01.3306 - Vara Única de Paulo Afonso-BA. Em 2015:
... A142: Legenda
A143: Símbolo | B143: Significado
A144: - | B144: Zero absoluto, não resultante de um cálculo ou arredondamento. Ex: Em determinado município não existem pessoas de 14 anos de idade sem instrução.
A145: 0 | B145: Zero resultante de um cálculo ou arredondamento. Ex: A inflação do feijão em determinada Região Metropolitana foi 0. Determinado município produziu 400 kg de sementes de girassol e os dados da tabela são expressos em toneladas.
A146: X | B146: Valor inibido para não identificar o informante. Ex: Determinado município só possui uma empresa produtora de cimento, logo o valor de sua produção deve ser inibido.
A147: .. | B147: Valor não se aplica. Ex: Não se pode obter o total da produção agrícola em determinado município quando os produtos agrícolas são contabilizados com unidades de medida distintas.
A148: ... | B148: Valor não disponível. Ex: A produção de feijão em determinado município não foi pesquisada ou determinado município não existia no ano da pesquisa.
A149: A a Z (exceto X) | B149: Significa uma faixa de valores. Varia em função da tabela (se for o caso). Ex: O nível de precisão da produção estimada de combustíveis está na faixa A (95 a 100%)
